ewmhlib/__init__.py
ewmhlib/_ewmhlib.py
ewmhlib/_main.py
ewmhlib/py.typed
ewmhlib/Props/__init__.py
ewmhlib/Props/_props.py
ewmhlib/Structs/__init__.py
ewmhlib/Structs/_structs.py
pywinctl/__init__.py
pywinctl/_main.py
pywinctl/_pywinctl_linux.py
pywinctl/_pywinctl_macos.py
pywinctl/_pywinctl_win.py
pywinctl/py.typed
PyWinCtl-0.2.dist-info/AUTHORS.txt
PyWinCtl-0.2.dist-info/LICENSE.txt
PyWinCtl-0.2.dist-info/METADATA
PyWinCtl-0.2.dist-info/WHEEL
PyWinCtl-0.2.dist-info/top_level.txt
PyWinCtl-0.2.dist-info/RECORD
