Metadata-Version: 2.1
Name: PyWinCtl
Version: 0.2
Summary: Cross-Platform toolkit to get info on and control windows on screen
Home-page: https://github.com/Kalmat/PyWinCtl
Author: Kalmat
Author-email: palookjones@gmail.com
License: BSD 3
Keywords: gui window control menu title name geometry size position move resize minimize maximize restore hide show activate raise lower close screen-size mouse-position
Classifier: Development Status :: 4 - Beta
Classifier: Environment :: Win32 (MS Windows)
Classifier: Environment :: X11 Applications
Classifier: Environment :: MacOS X
Classifier: Intended Audience :: Developers
Classifier: License :: OSI Approved :: BSD License
Classifier: Operating System :: OS Independent
Classifier: Programming Language :: Python
Classifier: Programming Language :: Python :: 3
Classifier: Programming Language :: Python :: 3 :: Only
Classifier: Programming Language :: Python :: 3.7
Classifier: Programming Language :: Python :: 3.8
Classifier: Programming Language :: Python :: 3.9
Classifier: Programming Language :: Python :: 3.10
Classifier: Programming Language :: Python :: 3.11
License-File: LICENSE.txt
License-File: AUTHORS.txt
Requires-Dist: typing-extensions (>=4.4.0)
Requires-Dist: pywinbox (>=0.6)
Requires-Dist: pymonctl (>=0.6)
Requires-Dist: pyobjc (>=8.1) ; sys_platform == "darwin"
Requires-Dist: python-xlib (>=0.21) ; sys_platform == "linux"
Requires-Dist: pywin32 (>=302) ; sys_platform == "win32"
Provides-Extra: dev
Requires-Dist: types-setuptools (>=65.5) ; extra == 'dev'
Requires-Dist: mypy (>=0.990) ; extra == 'dev'
Requires-Dist: types-pywin32 (>=305.0.0.3) ; extra == 'dev'
Requires-Dist: types-python-xlib (>=0.32) ; extra == 'dev'
